rtty_soda/__init__.py
rtty_soda/archivers.py
rtty_soda/cli/__init__.py
rtty_soda/cli/cli_options.py
rtty_soda/cli/cli_reader.py
rtty_soda/cli/cli_writer.py
rtty_soda/cli/main.py
rtty_soda/cli/main.pyi
rtty_soda/cryptography/__init__.py
rtty_soda/cryptography/kdf.py
rtty_soda/cryptography/public.py
rtty_soda/cryptography/secret.py
rtty_soda/encoders/__init__.py
rtty_soda/encoders/base26_encoder.py
rtty_soda/encoders/base31_encoder.py
rtty_soda/encoders/base36_encoder.py
rtty_soda/encoders/base64_encoder.py
rtty_soda/encoders/base94_encoder.py
rtty_soda/encoders/encoder.py
rtty_soda/encoders/functions.py
rtty_soda/encoders/scsu.py
rtty_soda/formatters.py
rtty_soda/interfaces.py
rtty_soda/py.typed
rtty_soda/services/__init__.py
rtty_soda/services/encoding_service.py
rtty_soda/services/encryption_service.py
rtty_soda/services/key_service.py
rtty_soda/services/service.py
rtty_soda-0.3.9.dist-info/WHEEL
rtty_soda-0.3.9.dist-info/entry_points.txt
rtty_soda-0.3.9.dist-info/METADATA
rtty_soda-0.3.9.dist-info/RECORD
