Metadata-Version: 2.3
Name: rtty-soda
Version: 0.3.9
Summary: A CLI tool for Unix-like environments to encrypt a RTTY session using NaCl
Keywords: cli,encryption,libsodium,nacl,rtty
Author: Theo Saveliev
Author-email: Theo Saveliev <89431871+theosaveliev@users.noreply.github.com>
License: MIT
Classifier: Development Status :: 4 - Beta
Classifier: Programming Language :: Python :: 3.14
Classifier: Operating System :: POSIX
Classifier: Environment :: Console
Classifier: License :: OSI Approved :: MIT License
Classifier: Topic :: Security :: Cryptography
Classifier: Topic :: Utilities
Requires-Dist: brotli>=1.2.0,<2.0.0
Requires-Dist: pynacl>=1.6.0,<2.0.0
Requires-Dist: scsu>=1.1.1,<2.0.0
Requires-Dist: click>=8.3.0,<9.0.0 ; extra == 'cli'
Requires-Dist: click-aliases>=1.0.5,<2.0.0 ; extra == 'cli'
Requires-Python: >=3.14, <4.0
Project-URL: github, https://github.com/theosaveliev/rtty-soda
Project-URL: issues, https://github.com/theosaveliev/rtty-soda/issues
Provides-Extra: cli
